README.md
setup.py
pvt/__init__.py
pvt/__main__.py
pvt/config.py
pvt/exceptions.py
pvt/project.py
pvt.egg-info/PKG-INFO
pvt.egg-info/SOURCES.txt
pvt.egg-info/dependency_links.txt
pvt.egg-info/entry_points.txt
pvt.egg-info/not-zip-safe
pvt.egg-info/requires.txt
pvt.egg-info/top_level.txt