Metadata-Version: 1.1
Name: pvt
Version: 0.0
Summary: Python virtual environment tool
Home-page: https://github.com/rcook/pvt
Author: Richard Cook
Author-email: rcook@rcook.org
License: MIT
Platform: UNKNOWN
Classifier: Development Status :: 3 - Alpha
Classifier: License :: OSI Approved :: MIT License
Classifier: Programming Language :: Python :: 2.7
